k8smtool
